Metadata-Version: 2.1
Name: odoo8-addon-framework-agreement
Version: 8.0.2.0.0.99.dev42
Summary: Long Term Agreement (or Framework Agreement) for purchases
Home-page: http://www.camptocamp.com
Author: Camptocamp,Odoo Community Association (OCA)
Author-email: support@odoo-community.org
License: AGPL-3
Platform: UNKNOWN
Classifier: Programming Language :: Python
Classifier: Framework :: Odoo
Classifier: Framework :: Odoo :: 8.0
Classifier: License :: OSI Approved :: GNU Affero General Public License v3
Requires-Python: ~=2.7
Requires-Dist: odoo8-addon-web-context-tunnel
Requires-Dist: odoo (<9.0a,>=8.0a)
